para_cli/__init__.py
para_cli/cli.py
para_cli/interactive.py
para_cli-0.1.1.dist-info/entry_points.txt
para_cli-0.1.1.dist-info/licenses/LICENSE
para_cli-0.1.1.dist-info/WHEEL
para_cli-0.1.1.dist-info/METADATA
para_cli-0.1.1.dist-info/RECORD
