Metadata-Version: 2.4
Name: para-cli
Version: 0.1.1
Summary: A command line tool for managing your PARA system
Keywords: para,productivity,organization,cli
Author-email: Azat <azataiot@gmail.com>
Requires-Python: >=3.13
Classifier: Development Status :: 3 - Alpha
Classifier: Environment :: Console
Classifier: Intended Audience :: End Users/Desktop
Classifier: License :: OSI Approved :: MIT License
Classifier: Programming Language :: Python :: 3
Classifier: Programming Language :: Python :: 3.13
Classifier: Topic :: Office/Business
Classifier: Topic :: Utilities
License-File: LICENSE
Requires-Dist: typer
Requires-Dist: rich
Requires-Dist: textual
Requires-Dist: textual ; extra == "interactive"
Project-URL: Documentation, https://github.com/azataiot/para-cli#readme
Project-URL: Home, https://github.com/azataiot/para-cli
Project-URL: Issues, https://github.com/azataiot/para-cli/issues
Provides-Extra: interactive
